odoo/addons/stock_account_move_reset_to_draft/README.rst
odoo/addons/stock_account_move_reset_to_draft/__init__.py
odoo/addons/stock_account_move_reset_to_draft/__manifest__.py
odoo/addons/stock_account_move_reset_to_draft/i18n/es.po
odoo/addons/stock_account_move_reset_to_draft/i18n/it.po
odoo/addons/stock_account_move_reset_to_draft/i18n/stock_account_move_reset_to_draft.pot
odoo/addons/stock_account_move_reset_to_draft/i18n/tr.po
odoo/addons/stock_account_move_reset_to_draft/models/__init__.py
odoo/addons/stock_account_move_reset_to_draft/models/account_move.py
odoo/addons/stock_account_move_reset_to_draft/readme/CONTEXT.md
odoo/addons/stock_account_move_reset_to_draft/readme/CONTRIBUTORS.md
odoo/addons/stock_account_move_reset_to_draft/readme/DESCRIPTION.md
odoo/addons/stock_account_move_reset_to_draft/readme/USAGE.md
odoo/addons/stock_account_move_reset_to_draft/static/description/icon.png
odoo/addons/stock_account_move_reset_to_draft/static/description/index.html
odoo/addons/stock_account_move_reset_to_draft/tests/__init__.py
odoo/addons/stock_account_move_reset_to_draft/tests/test_stock_account_move_reset_to_draft.py
odoo_addon_stock_account_move_reset_to_draft-18.0.1.0.0.7.dist-info/METADATA
odoo_addon_stock_account_move_reset_to_draft-18.0.1.0.0.7.dist-info/WHEEL
odoo_addon_stock_account_move_reset_to_draft-18.0.1.0.0.7.dist-info/top_level.txt
odoo_addon_stock_account_move_reset_to_draft-18.0.1.0.0.7.dist-info/RECORD
