Metadata-Version: 2.1
Name: odoo-addon-stock_account_move_reset_to_draft
Version: 18.0.1.0.0.7
Requires-Python: >=3.10
Requires-Dist: odoo==18.0.*
Summary: Stock account move reset to draft
Home-page: https://github.com/OCA/account-invoicing
License: AGPL-3
Author: Tecnativa, Odoo Community Association (OCA)
Author-email: support@odoo-community.org
Classifier: Programming Language :: Python
Classifier: Framework :: Odoo
Classifier: Framework :: Odoo :: 18.0
Classifier: License :: OSI Approved :: GNU Affero General Public License v3
